LICENSE
MANIFEST.in
README.md
setup.cfg
setup.py
assets/bar.png
assets/bar_h.png
assets/pie.png
reqs/app.in
reqs/app.txt
reqs/dev.in
reqs/dev.txt
src/termcharts/__init__.py
src/termcharts/bar_chart.py
src/termcharts/colors.py
src/termcharts/engine.py
src/termcharts/formula.py
src/termcharts/main.py
src/termcharts/pie.py
src/termcharts.egg-info/PKG-INFO
src/termcharts.egg-info/SOURCES.txt
src/termcharts.egg-info/dependency_links.txt
src/termcharts.egg-info/requires.txt
src/termcharts.egg-info/top_level.txt
src/termcharts/__pycache__/__init__.cpython-310.pyc
src/termcharts/__pycache__/bar.cpython-310.pyc
src/termcharts/__pycache__/bar_chart.cpython-310.pyc
src/termcharts/__pycache__/colors.cpython-310.pyc
src/termcharts/__pycache__/engine.cpython-310.pyc
src/termcharts/__pycache__/formula.cpython-310.pyc
src/termcharts/__pycache__/pepy.cpython-310.pyc
src/termcharts/__pycache__/pie.cpython-310.pyc
src/termcharts/__pycache__/pypistats.cpython-310.pyc