Metadata-Version: 2.1
Name: termcharts
Version: 1.1.2
Summary: Download stats for Python packages
Author-email: arj.python@gmail.com
Project-URL: Bug Reports, https://github.com/Abdur-RahmaanJ/termcharts/issues
Project-URL: Source, https://github.com/Abdur-RahmaanJ/termcharts/
Keywords: chart terminal plot cli command-line
Classifier: Development Status :: 4 - Beta
Classifier: Intended Audience :: Developers
Classifier: License :: OSI Approved :: MIT License
Classifier: Programming Language :: Python :: 3.7
Classifier: Programming Language :: Python :: 3.8
Classifier: Programming Language :: Python :: 3.9
Classifier: Programming Language :: Python :: 3.10
Classifier: Programming Language :: Python :: 3.11
Requires-Python: >=3.7
Provides-Extra: dev
Provides-Extra: rich
License-File: LICENSE
